nestmux/__init__.py
nestmux/cli.py
nestmux/lib.py
nestmux-0.1.4.dist-info/LICENSE
nestmux-0.1.4.dist-info/METADATA
nestmux-0.1.4.dist-info/WHEEL
nestmux-0.1.4.dist-info/entry_points.txt
nestmux-0.1.4.dist-info/RECORD
