Metadata-Version: 2.1
Name: nestmux
Version: 0.1.4
Summary: Run nested tmux sessions with ease
Home-page: https://github.com/oivvio/nestmux
Keywords: tmux,cli
Author: Oivvio Polite
Author-email: nestmux@liberationtech.net
Requires-Python: >=3.9,<4.0
Classifier: Programming Language :: Python :: 3
Classifier: Programming Language :: Python :: 3.9
Classifier: Programming Language :: Python :: 3.10
Classifier: Programming Language :: Python :: 3.11
Requires-Dist: libtmux (>=0.23.2,<0.24.0)
Requires-Dist: typer (>=0.9.0,<0.10.0)
Project-URL: Repository, https://github.com/oivvio/nestmux
